Workbook

Sheet Calculadora
A1: Costo y ganancia por franela
A2: Cambia solo las celdas amarillas (texto azul). Todo lo demás se calcula solo.
A4: DATOS
A5: Precio de la tela ($/kg) | B5: 8 | C5: Comprando por rollo cerrado. Referencia Caracas: $9–11/kg algodón blanco al mayor
A6: Gramaje de la tela (g/m²) | B6: 150 | C6: Jersey 30/1 ≈ 140–160. Mídelo: cuadrado de 10×10 cm en gramos × 100
A7: Tela por franela, promedio de tallas (m²) | B7: 1.2 | C7: Incluye desperdicio. Talla L ≈ 1,35 m²; S–XL mezcladas ≈ 1,2 m². Ajústalo con tu lote piloto
A8: Rib para el cuello (g por franela) | B8: 10
A9: Precio del rib ($/kg) | B9: 10
A10: Hilo por franela ($) | B10: 0.07 | C10: Overlock + recubridora. Un cono de ~$2 rinde ~30 franelas por hilo usado
A11: Etiqueta de talla ($) | B11: 0.03
A12: Bolsa / empaque por franela ($) | B12: 0.03 | C12: Si usas una bolsa por docena, divide su precio entre 12
A13: Luz, agujas, aceite, mantenimiento ($ por franela) | B13: 0.08 | C13: Estimado. Revísalo con tu recibo de luz y gastos del mes
A14: Merma / piezas dañadas (%) | B14: 0.03 | C14: Franelas que salen mal y no se pueden vender
A15: Precio de venta por franela ($) | B15: 3 | C15: Vendiendo por docena: $3 × 12 = $36 la docena
A16: Margen que quieres ganar (%) | B16: 0.3 | C16: Para calcular el precio mínimo recomendado
A18: RESULTADOS POR FRANELA
A19: Tela usada (gramos) | B19: =B6*B7 -> 180
A20: Franelas por rollo de 25 kg | B20: =IF(B19>0,25000/B19,0) -> 138.88889
A21: Costo de la tela | B21: =B19/1000*B5 -> 1.44
A22: Costo del rib | B22: =B8/1000*B9 -> 0.1
A23: Otros insumos (hilo, etiqueta, bolsa, luz) | B23: =B10+B11+B12+B13 -> 0.21
A24: Costo antes de merma | B24: =B21+B22+B23 -> 1.75
A25: Costo por merma | B25: =B24*B14 -> 0.0525
A26: COSTO TOTAL POR FRANELA | B26: =B24+B25 -> 1.8025 | C26: No incluye su mano de obra: la ganancia es su pago
A27: GANANCIA POR FRANELA | B27: =B15-B26 -> 1.1975
A28: Margen | B28: =IF(B15>0,B27/B15,0) -> 0.39916667
A30: POR DOCENA
A31: Precio de venta por docena | B31: =B15*12 -> 36
A32: Costo por docena | B32: =B26*12 -> 21.63
A33: GANANCIA POR DOCENA | B33: =B27*12 -> 14.37
A35: PRECIO RECOMENDADO
A36: Precio mínimo por franela para tu margen | B36: =IF(B16<1,B26/(1-B16),0) -> 2.575 | C36: Con el margen de la celda B16
A37: Precio mínimo por docena para tu margen | B37: =B36*12 -> 30.9
A39: Leyenda: celdas amarillas con texto azul = datos que tú cambias · celdas verdes = resultados clave.
A40: Los valores de ejemplo son estimados de referencia (Venezuela, oct. 2026). Reemplázalos con tus costos reales.

Sheet Produccion
A1: Producción, ganancia mensual e inversión
A2: Para dos personas cosiendo en casa. Usa los costos de la hoja Calculadora.
A4: DATOS DE PRODUCCIÓN
A5: Franelas terminadas por día (entre los dos) | B5: 50 | C5: Incluye cortar, coser, revisar y empacar. Empezando puede ser 30–40; con práctica 60–80
A6: Días de trabajo al mes | B6: 22
A7: Horas de trabajo por día | B7: 8
A8: Personas | B8: 2
A9: Peso de un rollo (kg) | B9: 25
A11: INVERSIÓN EN MÁQUINAS (estimados, cotiza en tu zona)
A12: Overlock industrial 4 hilos ($) | B12: 500 | C12: Para cerrar costados, hombros y pegar mangas
A13: Recubridora / collareta industrial ($) | B13: 700 | C13: Para ruedos de manga y bajo. Es la que da el acabado profesional
A14: Máquina recta industrial ($) | B14: 300 | C14: Opcional al inicio: para etiquetas y pespuntes
A15: Cortadora de tela (circular o vertical) ($) | B15: 250 | C15: Para cortar varias capas a la vez
A16: Mesa de corte, tijeras, reglas, moldes ($) | B16: 150
A17: Total inversión | B17: =SUM(B12:B16) -> 1900
A18: Vida útil de las máquinas (meses) | B18: 36 | C18: Para repartir el costo de las máquinas en el tiempo
A20: RESULTADOS DEL MES
A21: Franelas al mes | B21: =B5*B6 -> 1100
A22: Docenas al mes | B22: =B21/12 -> 91.666667
A23: Tela necesaria (kg) | B23: =B21*Calculadora!B19/1000 -> 198
A24: Rollos al mes | B24: =IF(B9>0,B23/B9,0) -> 7.92
A25: Ventas al mes | B25: =B21*Calculadora!B15 -> 3300
A26: Dinero para materiales al mes (capital de trabajo) | B26: =B21*Calculadora!B26 -> 1982.75 | C26: Lo que necesitan tener disponible para comprar tela e insumos
A27: Ganancia al mes antes de máquinas | B27: =B21*Calculadora!B27 -> 1317.25
A28: Desgaste de máquinas al mes | B28: =IF(B18>0,B17/B18,0) -> 52.777778
A29: GANANCIA NETA AL MES (los dos) | B29: =B27-B28 -> 1264.4722 | C29: Este es el pago de su trabajo
A30: Ganancia por persona al mes | B30: =IF(B8>0,B29/B8,0) -> 632.23611
A31: Ganancia por hora, por persona | B31: =IF(B8*B6*B7>0,B29/(B8*B6*B7),0) -> 3.5922506
A32: Meses para recuperar la inversión en máquinas | B32: =IF(B27>0,B17/B27,0) -> 1.4423989
A34: Importante: estos números suponen que venden todo lo que producen. Si venden menos, baja la ganancia, no el costo por franela.

Sheet Sensibilidad
A1: Ganancia por DOCENA según precio de tela y precio de venta
A2: Usa los demás costos de la hoja Calculadora. Verde: buena · Amarillo: justa · Rojo: muy poca o pérdida.
A4: Precio tela ($/kg) ↓ · Precio venta por franela →
B5: 2.5 | C5: 2.75 | D5: 3 | E5: 3.25 | F5: 3.5 | G5: 3.75 | H5: 4
A6: 6 | B6: =(B$5-(($A6*Calculadora!$B$19/1000)+Calculadora!$B$22+Calculadora!$B$23)*(1+Calculadora!$B$14))*12 -> 12.8196 | C6: =(C$5-(($A6*Calculadora!$B$19/1000)+Calculadora!$B$22+Calculadora!$B$23)*(1+Calculadora!$B$14))*12 -> 15.8196 | D6: =(D$5-(($A6*Calculadora!$B$19/1000)+Calculadora!$B$22+Calculadora!$B$23)*(1+Calculadora!$B$14))*12 -> 18.8196 | E6: =(E$5-(($A6*Calculadora!$B$19/1000)+Calculadora!$B$22+Calculadora!$B$23)*(1+Calculadora!$B$14))*12 -> 21.8196 | F6: =(F$5-(($A6*Calculadora!$B$19/1000)+Calculadora!$B$22+Calculadora!$B$23)*(1+Calculadora!$B$14))*12 -> 24.8196 | G6: =(G$5-(($A6*Calculadora!$B$19/1000)+Calculadora!$B$22+Calculadora!$B$23)*(1+Calculadora!$B$14))*12 -> 27.8196 | H6: =(H$5-(($A6*Calculadora!$B$19/1000)+Calculadora!$B$22+Calculadora!$B$23)*(1+Calculadora!$B$14))*12 -> 30.8196
A7: 7 | B7: =(B$5-(($A7*Calculadora!$B$19/1000)+Calculadora!$B$22+Calculadora!$B$23)*(1+Calculadora!$B$14))*12 -> 10.5948 | C7: =(C$5-(($A7*Calculadora!$B$19/1000)+Calculadora!$B$22+Calculadora!$B$23)*(1+Calculadora!$B$14))*12 -> 13.5948 | D7: =(D$5-(($A7*Calculadora!$B$19/1000)+Calculadora!$B$22+Calculadora!$B$23)*(1+Calculadora!$B$14))*12 -> 16.5948 | E7: =(E$5-(($A7*Calculadora!$B$19/1000)+Calculadora!$B$22+Calculadora!$B$23)*(1+Calculadora!$B$14))*12 -> 19.5948 | F7: =(F$5-(($A7*Calculadora!$B$19/1000)+Calculadora!$B$22+Calculadora!$B$23)*(1+Calculadora!$B$14))*12 -> 22.5948 | G7: =(G$5-(($A7*Calculadora!$B$19/1000)+Calculadora!$B$22+Calculadora!$B$23)*(1+Calculadora!$B$14))*12 -> 25.5948 | H7: =(H$5-(($A7*Calculadora!$B$19/1000)+Calculadora!$B$22+Calculadora!$B$23)*(1+Calculadora!$B$14))*12 -> 28.5948
A8: 8 | B8: =(B$5-(($A8*Calculadora!$B$19/1000)+Calculadora!$B$22+Calculadora!$B$23)*(1+Calculadora!$B$14))*12 -> 8.37 | C8: =(C$5-(($A8*Calculadora!$B$19/1000)+Calculadora!$B$22+Calculadora!$B$23)*(1+Calculadora!$B$14))*12 -> 11.37 | D8: =(D$5-(($A8*Calculadora!$B$19/1000)+Calculadora!$B$22+Calculadora!$B$23)*(1+Calculadora!$B$14))*12 -> 14.37 | E8: =(E$5-(($A8*Calculadora!$B$19/1000)+Calculadora!$B$22+Calculadora!$B$23)*(1+Calculadora!$B$14))*12 -> 17.37 | F8: =(F$5-(($A8*Calculadora!$B$19/1000)+Calculadora!$B$22+Calculadora!$B$23)*(1+Calculadora!$B$14))*12 -> 20.37 | G8: =(G$5-(($A8*Calculadora!$B$19/1000)+Calculadora!$B$22+Calculadora!$B$23)*(1+Calculadora!$B$14))*12 -> 23.37 | H8: =(H$5-(($A8*Calculadora!$B$19/1000)+Calculadora!$B$22+Calculadora!$B$23)*(1+Calculadora!$B$14))*12 -> 26.37
A9: 9 | B9: =(B$5-(($A9*Calculadora!$B$19/1000)+Calculadora!$B$22+Calculadora!$B$23)*(1+Calculadora!$B$14))*12 -> 6.1452 | C9: =(C$5-(($A9*Calculadora!$B$19/1000)+Calculadora!$B$22+Calculadora!$B$23)*(1+Calculadora!$B$14))*12 -> 9.1452 | D9: =(D$5-(($A9*Calculadora!$B$19/1000)+Calculadora!$B$22+Calculadora!$B$23)*(1+Calculadora!$B$14))*12 -> 12.1452 | E9: =(E$5-(($A9*Calculadora!$B$19/1000)+Calculadora!$B$22+Calculadora!$B$23)*(1+Calculadora!$B$14))*12 -> 15.1452 | F9: =(F$5-(($A9*Calculadora!$B$19/1000)+Calculadora!$B$22+Calculadora!$B$23)*(1+Calculadora!$B$14))*12 -> 18.1452 | G9: =(G$5-(($A9*Calculadora!$B$19/1000)+Calculadora!$B$22+Calculadora!$B$23)*(1+Calculadora!$B$14))*12 -> 21.1452 | H9: =(H$5-(($A9*Calculadora!$B$19/1000)+Calculadora!$B$22+Calculadora!$B$23)*(1+Calculadora!$B$14))*12 -> 24.1452
A10: 10 | B10: =(B$5-(($A10*Calculadora!$B$19/1000)+Calculadora!$B$22+Calculadora!$B$23)*(1+Calculadora!$B$14))*12 -> 3.9204 | C10: =(C$5-(($A10*Calculadora!$B$19/1000)+Calculadora!$B$22+Calculadora!$B$23)*(1+Calculadora!$B$14))*12 -> 6.9204 | D10: =(D$5-(($A10*Calculadora!$B$19/1000)+Calculadora!$B$22+Calculadora!$B$23)*(1+Calculadora!$B$14))*12 -> 9.9204 | E10: =(E$5-(($A10*Calculadora!$B$19/1000)+Calculadora!$B$22+Calculadora!$B$23)*(1+Calculadora!$B$14))*12 -> 12.9204 | F10: =(F$5-(($A10*Calculadora!$B$19/1000)+Calculadora!$B$22+Calculadora!$B$23)*(1+Calculadora!$B$14))*12 -> 15.9204 | G10: =(G$5-(($A10*Calculadora!$B$19/1000)+Calculadora!$B$22+Calculadora!$B$23)*(1+Calculadora!$B$14))*12 -> 18.9204 | H10: =(H$5-(($A10*Calculadora!$B$19/1000)+Calculadora!$B$22+Calculadora!$B$23)*(1+Calculadora!$B$14))*12 -> 21.9204
A11: 11 | B11: =(B$5-(($A11*Calculadora!$B$19/1000)+Calculadora!$B$22+Calculadora!$B$23)*(1+Calculadora!$B$14))*12 -> 1.6956 | C11: =(C$5-(($A11*Calculadora!$B$19/1000)+Calculadora!$B$22+Calculadora!$B$23)*(1+Calculadora!$B$14))*12 -> 4.6956 | D11: =(D$5-(($A11*Calculadora!$B$19/1000)+Calculadora!$B$22+Calculadora!$B$23)*(1+Calculadora!$B$14))*12 -> 7.6956 | E11: =(E$5-(($A11*Calculadora!$B$19/1000)+Calculadora!$B$22+Calculadora!$B$23)*(1+Calculadora!$B$14))*12 -> 10.6956 | F11: =(F$5-(($A11*Calculadora!$B$19/1000)+Calculadora!$B$22+Calculadora!$B$23)*(1+Calculadora!$B$14))*12 -> 13.6956 | G11: =(G$5-(($A11*Calculadora!$B$19/1000)+Calculadora!$B$22+Calculadora!$B$23)*(1+Calculadora!$B$14))*12 -> 16.6956 | H11: =(H$5-(($A11*Calculadora!$B$19/1000)+Calculadora!$B$22+Calculadora!$B$23)*(1+Calculadora!$B$14))*12 -> 19.6956
A12: 12 | B12: =(B$5-(($A12*Calculadora!$B$19/1000)+Calculadora!$B$22+Calculadora!$B$23)*(1+Calculadora!$B$14))*12 -> -0.5292 | C12: =(C$5-(($A12*Calculadora!$B$19/1000)+Calculadora!$B$22+Calculadora!$B$23)*(1+Calculadora!$B$14))*12 -> 2.4708 | D12: =(D$5-(($A12*Calculadora!$B$19/1000)+Calculadora!$B$22+Calculadora!$B$23)*(1+Calculadora!$B$14))*12 -> 5.4708 | E12: =(E$5-(($A12*Calculadora!$B$19/1000)+Calculadora!$B$22+Calculadora!$B$23)*(1+Calculadora!$B$14))*12 -> 8.4708 | F12: =(F$5-(($A12*Calculadora!$B$19/1000)+Calculadora!$B$22+Calculadora!$B$23)*(1+Calculadora!$B$14))*12 -> 11.4708 | G12: =(G$5-(($A12*Calculadora!$B$19/1000)+Calculadora!$B$22+Calculadora!$B$23)*(1+Calculadora!$B$14))*12 -> 14.4708 | H12: =(H$5-(($A12*Calculadora!$B$19/1000)+Calculadora!$B$22+Calculadora!$B$23)*(1+Calculadora!$B$14))*12 -> 17.4708
A14: Cómo leerla: busca tu precio de tela (fila) y tu precio de venta (columna). El número es lo que ganan por cada docena vendida.
A15: Rojo < $6 por docena · Amarillo $6–10 · Verde ≥ $10. Puedes cambiar los precios de las filas y columnas.
